100cli-0.0.1.dist-info/licenses/LICENSE
hundredcli/__init__.py
hundredcli/main.py
hundredcli/UI/__init__.py
hundredcli/UI/display.py
100cli-0.0.1.dist-info/METADATA
100cli-0.0.1.dist-info/WHEEL
100cli-0.0.1.dist-info/entry_points.txt
100cli-0.0.1.dist-info/top_level.txt
100cli-0.0.1.dist-info/RECORD
