Metadata-Version: 2.4
Name: 100cli
Version: 0.0.1
Summary: 🤖 The 100 LoC CLI agent made to be hacked — simple, easy to understand, and hackable ✨
Author-email: Bhavnick Minhas <bhavnick@chonkie.ai>
Maintainer-email: Bhavnick Minhas <bhavnick@chonkie.ai>
License: MIT License
Project-URL: Homepage, https://github.com/chonknick/100cli
Project-URL: Documentation, https://github.com/chonknick/100cli
Project-URL: Bug Tracker, https://github.com/chonknick/100cli/issues
Keywords: CLI,artificial-intelligence,agents
Classifier: Programming Language :: Python
Classifier: Programming Language :: Python :: 3
Classifier: Programming Language :: Python :: 3.10
Classifier: Programming Language :: Python :: 3.11
Classifier: Programming Language :: Python :: 3.12
Classifier: Programming Language :: Python :: 3.13
Classifier: Intended Audience :: Developers
Classifier: Intended Audience :: Science/Research
Classifier: Intended Audience :: Information Technology
Classifier: Topic :: Scientific/Engineering :: Artificial Intelligence
Classifier: Topic :: Scientific/Engineering :: Information Analysis
Classifier: Topic :: Text Processing :: Linguistic
Requires-Python: >=3.10
License-File: LICENSE
Requires-Dist: typer>=0.16.0
Requires-Dist: rich>=13.0.0
Provides-Extra: openai
Requires-Dist: openai>=1.0.0; extra == "openai"
Dynamic: license-file
